pytest_litter/__init__.py
pytest_litter/snapshots.py
pytest_litter/plugin/__init__.py
pytest_litter/plugin/plugin.py
pytest_litter/plugin/utils.py
pytest_litter-0.0.4.dist-info/LICENSE
pytest_litter-0.0.4.dist-info/METADATA
pytest_litter-0.0.4.dist-info/WHEEL
pytest_litter-0.0.4.dist-info/entry_points.txt
pytest_litter-0.0.4.dist-info/top_level.txt
pytest_litter-0.0.4.dist-info/RECORD
