Metadata-Version: 2.1
Name: pytest-litter
Version: 0.0.4
Summary: Pytest plugin which verifies that tests do not modify file trees.
Author: Anton Vikström
License: Apache License
Project-URL: repo, https://github.com/mam-dev/pytest-litter
Classifier: Development Status :: 4 - Beta
Classifier: Programming Language :: Python :: 3.9
Classifier: Programming Language :: Python :: 3.10
Classifier: Programming Language :: Python :: 3.11
Classifier: Programming Language :: Python :: 3.12
Classifier: Topic :: Software Development :: Testing
Classifier: Topic :: Software Development :: Testing :: Unit
Classifier: Framework :: Pytest
Classifier: License :: OSI Approved :: Apache Software License
Requires-Python: >=3.9
License-File: LICENSE
Requires-Dist: pytest >=6.1
